LICENSE.txt
README.md
setup.cfg
setup.py
pinsta/Authentication.py
pinsta/AutoHost.py
pinsta/Guest.py
pinsta/Host.py
pinsta/__init__.py
pinsta.egg-info/PKG-INFO
pinsta.egg-info/SOURCES.txt
pinsta.egg-info/dependency_links.txt
pinsta.egg-info/requires.txt
pinsta.egg-info/top_level.txt
pinsta/containers/FollowPerson.py
pinsta/containers/FollowedStatus.py
pinsta/containers/Liker.py
pinsta/containers/Likers.py
pinsta/containers/Post.py
pinsta/containers/PostUser.py
pinsta/containers/Profile.py
pinsta/containers/ProfileHost.py
pinsta/containers/UnfollowedStatus.py
pinsta/containers/__init__.py
pinsta/lib/Commons.py
pinsta/lib/Exceptions.py
pinsta/lib/__init__.py