Metadata-Version: 2.1
Name: pinsta
Version: 3.0
Summary: 🔥 Fastest & Simplest Python Package For Instagram Automation
Home-page: https://github.com/diezo/pinsta
Download-URL: https://github.com/diezo/pinsta/archive/refs/tags/v2.9.tar.gz
Author: Deepak Soni
Author-email: lonelycube@proton.me
License: MIT
Keywords: instagram-client,instagram,api-wrapper,instagram-scraper,instagram-api,instagram-sdk,instagram-photos,instagram-api-python,instabot,instagram-stories,instagram-bot,instapy,instagram-downloader,instagram-account,instagram-crawler,instagram-private-api,igtv,instagram-automation,reels,instagram-feed
Classifier: Development Status :: 5 - Production/Stable
Classifier: Intended Audience :: Developers
Classifier: Topic :: Software Development :: Build Tools
Classifier: License :: OSI Approved :: MIT License
Classifier: Programming Language :: Python :: 3
Classifier: Programming Language :: Python :: 3.10
License-File: LICENSE.txt
